max.py
maxbatalwebscraping-0.0.1.dist-info/LICENSE.txt
maxbatalwebscraping-0.0.1.dist-info/METADATA
maxbatalwebscraping-0.0.1.dist-info/WHEEL
maxbatalwebscraping-0.0.1.dist-info/top_level.txt
maxbatalwebscraping-0.0.1.dist-info/RECORD
